piteau/__init__.py
piteau/base/__init__.py
piteau/base/client.py
piteau/base/server.py
piteau/exceptions.py
piteau-0.1.2.dist-info/WHEEL
piteau-0.1.2.dist-info/METADATA
piteau-0.1.2.dist-info/RECORD
